{
  "name": "Вывих ноги (Лечено)",
  "type": "effect",
  "img": "icons/skills/wounds/anatomy-bone-joint.webp",
  "effects": [],
  "flags": {
    "cf": {
      "id": "temp_n2afsx7fi5j"
    }
  },
  "system": {
    "description": "После удара нога персонажа вывихнута, она плохо слушается и на неё больно наступать.",
    "isActive": true,
    "stats": [
      {
        "id": "first",
        "stat": "WITCHER.Actor.Stat.Spd",
        "modifier": "-1"
      }
    ],
    "derived": [],
    "skills": []
  },
  "_stats": {
    "systemId": "TheWitcherTRPG",
    "systemVersion": "0.96",
    "coreVersion": "11.299",
    "createdTime": 1668162883167,
    "modifiedTime": 1685496621796,
    "lastModifiedBy": "SFdeLroDgLgy3uI9"
  },
  "_id": "bUCoMIbwheOmoJVM",
  "folder": "i9IWaFNhx9E6aUgp",
  "sort": 0,
  "ownership": {
    "default": 0,
    "TzUlXsBoDDaZxlVp": 3
  },
  "_key": "!items!bUCoMIbwheOmoJVM"
}