{
  "name": "Лунный клинок",
  "type": "weapon",
  "img": "icons/weapons/swords/greatsword-crossguard-flanged-purple.webp",
  "effects": [],
  "flags": {
    "core": {
      "sourceId": "Compendium.world.relikvii-oruzhiya.VILXCwPSN8jDiMpM"
    },
    "cf": {
      "id": "temp_158empsijjm"
    },
    "autoanimations": {
      "id": "511943b7-77ab-44b7-97c0-89afc2cb664b",
      "label": "Лунный клинок",
      "levels3d": {
        "type": "explosion",
        "data": {
          "color01": "#FFFFFF",
          "color02": "#FFFFFF",
          "spritePath": "modules/levels-3d-preview/assets/particles/dust.png"
        },
        "sound": {
          "enable": false
        },
        "secondary": {
          "enable": false,
          "data": {
            "color01": "#FFFFFF",
            "color02": "#FFFFFF",
            "spritePath": "modules/levels-3d-preview/assets/particles/dust.png"
          }
        }
      },
      "macro": {
        "enable": false,
        "playWhen": "0"
      },
      "meleeSwitch": {
        "video": {
          "dbSection": "range",
          "menuType": "weapon",
          "animation": "arrow",
          "variant": "regular",
          "color": "regular"
        },
        "sound": {
          "enable": false,
          "delay": 0,
          "repeat": 1,
          "repeatDelay": 250,
          "startTime": 0,
          "volume": 0.75
        },
        "options": {
          "detect": "automatic",
          "range": 2,
          "returning": false,
          "switchType": "on"
        }
      },
      "menu": "melee",
      "primary": {
        "video": {
          "dbSection": "melee",
          "menuType": "weapon",
          "animation": "greatsword",
          "variant": "01",
          "color": "white",
          "enableCustom": false,
          "customPath": ""
        },
        "sound": {
          "enable": false,
          "delay": 0,
          "repeat": 1,
          "repeatDelay": 250,
          "startTime": 0,
          "volume": 0.75
        },
        "options": {
          "contrast": 0,
          "delay": 0,
          "elevation": 1000,
          "isWait": false,
          "opacity": 1,
          "playbackRate": 1,
          "repeat": 1,
          "repeatDelay": 250,
          "saturate": 0,
          "size": 1,
          "tint": false,
          "tintColor": "#FFFFFF",
          "zIndex": 1
        }
      },
      "secondary": {
        "enable": false,
        "video": {
          "dbSection": "static",
          "menuType": "spell",
          "animation": "curewounds",
          "variant": "01",
          "color": "blue",
          "enableCustom": false,
          "customPath": ""
        },
        "sound": {
          "enable": false,
          "delay": 0,
          "repeat": 1,
          "repeatDelay": 250,
          "startTime": 0,
          "volume": 0.75
        },
        "options": {
          "addTokenWidth": false,
          "anchor": "0.5",
          "contrast": 0,
          "delay": 0,
          "elevation": 1000,
          "fadeIn": 250,
          "fadeOut": 500,
          "isMasked": false,
          "isRadius": true,
          "isWait": false,
          "opacity": 1,
          "repeat": 1,
          "repeatDelay": 250,
          "saturate": 0,
          "size": 1.5,
          "tint": false,
          "tintColor": "#FFFFFF",
          "zIndex": 1
        }
      },
      "soundOnly": {
        "sound": {
          "enable": false,
          "delay": 0,
          "repeat": 1,
          "repeatDelay": 250,
          "startTime": 0,
          "volume": 0.75
        }
      },
      "source": {
        "enable": false,
        "video": {
          "dbSection": "static",
          "menuType": "spell",
          "animation": "curewounds",
          "variant": "01",
          "color": "blue",
          "enableCustom": false,
          "customPath": ""
        },
        "sound": {
          "enable": false,
          "delay": 0,
          "repeat": 1,
          "repeatDelay": 250,
          "startTime": 0,
          "volume": 0.75
        },
        "options": {
          "addTokenWidth": false,
          "anchor": "0.5",
          "contrast": 0,
          "delay": 0,
          "elevation": 1000,
          "fadeIn": 250,
          "fadeOut": 500,
          "isMasked": false,
          "isRadius": false,
          "isWait": true,
          "opacity": 1,
          "repeat": 1,
          "repeatDelay": 250,
          "saturate": 0,
          "size": 1,
          "tint": false,
          "tintColor": "#FFFFFF",
          "zIndex": 1
        }
      },
      "target": {
        "enable": false,
        "video": {
          "dbSection": "static",
          "menuType": "spell",
          "animation": "curewounds",
          "variant": "01",
          "color": "blue",
          "enableCustom": false,
          "customPath": ""
        },
        "sound": {
          "enable": false,
          "delay": 0,
          "repeat": 1,
          "repeatDelay": 250,
          "startTime": 0,
          "volume": 0.75
        },
        "options": {
          "addTokenWidth": false,
          "anchor": "0.5",
          "contrast": 0,
          "delay": 0,
          "elevation": 1000,
          "fadeIn": 250,
          "fadeOut": 500,
          "isMasked": false,
          "isRadius": false,
          "opacity": 1,
          "persistent": false,
          "repeat": 1,
          "repeatDelay": 250,
          "saturate": 0,
          "size": 1,
          "tint": false,
          "tintColor": "#FFFFFF",
          "unbindAlpha": false,
          "unbindVisibility": false,
          "zIndex": 1
        }
      },
      "isEnabled": true,
      "isCustomized": true,
      "fromAmmo": false,
      "version": 5
    }
  },
  "system": {
    "description": "",
    "quantity": 1,
    "weight": 4,
    "cost": null,
    "isHidden": false,
    "associatedDiagram": {},
    "type": {
      "text": "Рубящее, Колющее",
      "slashing": true,
      "piercing": true,
      "bludgeoning": false,
      "elemental": false
    },
    "isAmmo": false,
    "usingAmmo": false,
    "accuracy": 1,
    "avail": "Rare",
    "damage": "3d6",
    "reliable": 10,
    "maxReliability": 10,
    "hands": "2",
    "range": "",
    "equiped": false,
    "effects": [
      {
        "id": "first",
        "name": "Серебряное(7d6+4)",
        "percentage": ""
      },
      {
        "id": "_2ltc8r2yt",
        "name": "Улучшенный фокус",
        "percentage": ""
      }
    ],
    "conceal": "NA",
    "enhancements": 3,
    "enhancementItems": [],
    "rateOfFire": 1,
    "attackSkill": "Swordsmanship",
    "rollOnlyDmg": false,
    "isThrowable": false
  },
  "_stats": {
    "systemId": "TheWitcherTRPG",
    "systemVersion": "0.96",
    "coreVersion": "11.304",
    "createdTime": 1668162877955,
    "modifiedTime": 1688757684284,
    "lastModifiedBy": "Rcr49y7kKhnhIeHT"
  },
  "_id": "ruaBPSVzlb1OTb12",
  "folder": "qosTfu30dYf09sIj",
  "sort": 0,
  "ownership": {
    "default": 0,
    "TzUlXsBoDDaZxlVp": 3
  },
  "_key": "!items!ruaBPSVzlb1OTb12"
}