{
  "name": "Пурга",
  "type": "alchemical",
  "img": "modules/the-ultimate-witcher/assets/potions/blizzard.png",
  "system": {
    "description": "",
    "quantity": 1,
    "weight": 0.5,
    "cost": 32,
    "isHidden": false,
    "associatedDiagram": {},
    "type": "potion",
    "avail": "Rare",
    "effect": "+4 к Реа после убийства противника. Последу-\nющие убийства не увеличивают бонус, который\nдлится, пока действует эликсир.",
    "time": "10 раундов",
    "toxicity": "75%"
  },
  "sort": 500000,
  "ownership": {
    "default": 0,
    "TzUlXsBoDDaZxlVp": 3,
    "92kKQj5Pnu6fnA0z": 3
  },
  "flags": {
    "cf": {
      "id": "temp_ablplrf0fnm"
    },
    "core": {
      "sourceId": "Compendium.the-ultimate-witcher.vedmache-snaryazhenie.5fPhdjHiPsZOea8g"
    }
  },
  "_stats": {
    "systemId": "TheWitcherTRPG",
    "systemVersion": "0.94",
    "coreVersion": "10.290",
    "createdTime": 1668162887309,
    "modifiedTime": 1671035867932,
    "lastModifiedBy": "92kKQj5Pnu6fnA0z"
  },
  "_id": "j3Bfu7qcrkHCHpnY",
  "effects": [],
  "folder": null,
  "_key": "!actors.items!k7OKybGxBGmKX5AY.j3Bfu7qcrkHCHpnY"
}