{
  "name": "Адэнидд",
  "type": "spell",
  "img": "icons/magic/control/debuff-energy-snare-blue.webp",
  "effects": [],
  "flags": {
    "cf": {
      "id": "temp_cilmpkpuxju"
    },
    "autoanimations": {
      "id": "2b7673ab-925a-4ccc-94c5-6aa4fd516958",
      "label": "Адэнидд",
      "levels3d": {
        "type": "explosion",
        "data": {
          "color01": "#FFFFFF",
          "color02": "#FFFFFF",
          "spritePath": "modules/levels-3d-preview/assets/particles/dust.png"
        },
        "sound": {
          "enable": false
        },
        "secondary": {
          "enable": false,
          "data": {
            "color01": "#FFFFFF",
            "color02": "#FFFFFF",
            "spritePath": "modules/levels-3d-preview/assets/particles/dust.png"
          }
        }
      },
      "macro": {
        "enable": false,
        "playWhen": "0"
      },
      "menu": "ontoken",
      "primary": {
        "video": {
          "dbSection": "static",
          "menuType": "energy",
          "animation": "sparkles",
          "variant": "01",
          "color": "blue",
          "enableCustom": false,
          "customPath": ""
        },
        "sound": {
          "enable": false,
          "delay": 0,
          "repeat": 1,
          "repeatDelay": 250,
          "startTime": 0,
          "volume": 0.75
        },
        "options": {
          "addTokenWidth": false,
          "anchor": "0.5",
          "contrast": 0,
          "delay": 0,
          "elevation": 1000,
          "fadeIn": 250,
          "fadeOut": 500,
          "isMasked": false,
          "isRadius": false,
          "isWait": false,
          "opacity": 1,
          "persistent": false,
          "playbackRate": 1,
          "playOn": "source",
          "repeat": 1,
          "repeatDelay": 250,
          "saturate": 0,
          "size": 1,
          "tint": false,
          "tintColor": "#FFFFFF",
          "unbindAlpha": false,
          "unbindVisibility": false,
          "zIndex": 1
        }
      },
      "secondary": {
        "enable": false,
        "video": {
          "dbSection": "static",
          "menuType": "spell",
          "animation": "curewounds",
          "variant": "01",
          "color": "blue",
          "enableCustom": false,
          "customPath": ""
        },
        "sound": {
          "enable": false,
          "delay": 0,
          "repeat": 1,
          "repeatDelay": 250,
          "startTime": 0,
          "volume": 0.75
        },
        "options": {
          "addTokenWidth": false,
          "anchor": "0.5",
          "contrast": 0,
          "delay": 0,
          "elevation": 1000,
          "fadeIn": 250,
          "fadeOut": 500,
          "isMasked": false,
          "isRadius": true,
          "isWait": false,
          "opacity": 1,
          "repeat": 1,
          "repeatDelay": 250,
          "saturate": 0,
          "size": 1.5,
          "tint": false,
          "tintColor": "#FFFFFF",
          "zIndex": 1
        }
      },
      "soundOnly": {
        "sound": {
          "enable": false,
          "delay": 0,
          "repeat": 1,
          "repeatDelay": 250,
          "startTime": 0,
          "volume": 0.75
        }
      },
      "source": {
        "enable": false,
        "video": {
          "dbSection": "static",
          "menuType": "spell",
          "animation": "curewounds",
          "variant": "01",
          "color": "blue",
          "enableCustom": false,
          "customPath": ""
        },
        "sound": {
          "enable": false,
          "delay": 0,
          "repeat": 1,
          "repeatDelay": 250,
          "startTime": 0,
          "volume": 0.75
        },
        "options": {
          "addTokenWidth": false,
          "anchor": "0.5",
          "contrast": 0,
          "delay": 0,
          "elevation": 1000,
          "fadeIn": 250,
          "fadeOut": 500,
          "isMasked": false,
          "isRadius": false,
          "isWait": true,
          "opacity": 1,
          "repeat": 1,
          "repeatDelay": 250,
          "saturate": 0,
          "size": 1,
          "tint": false,
          "tintColor": "#FFFFFF",
          "zIndex": 1
        }
      },
      "target": {
        "enable": false,
        "video": {
          "dbSection": "static",
          "menuType": "spell",
          "animation": "curewounds",
          "variant": "01",
          "color": "blue",
          "enableCustom": false,
          "customPath": ""
        },
        "sound": {
          "enable": false,
          "delay": 0,
          "repeat": 1,
          "repeatDelay": 250,
          "startTime": 0,
          "volume": 0.75
        },
        "options": {
          "addTokenWidth": false,
          "anchor": "0.5",
          "contrast": 0,
          "delay": 0,
          "elevation": 1000,
          "fadeIn": 250,
          "fadeOut": 500,
          "isMasked": false,
          "isRadius": false,
          "opacity": 1,
          "persistent": false,
          "repeat": 1,
          "repeatDelay": 250,
          "saturate": 0,
          "size": 1,
          "tint": false,
          "tintColor": "#FFFFFF",
          "unbindAlpha": false,
          "unbindVisibility": false,
          "zIndex": 1
        }
      },
      "isEnabled": true,
      "isCustomized": true,
      "fromAmmo": false,
      "version": 5
    }
  },
  "system": {
    "class": "Spells",
    "level": "novice",
    "source": "air",
    "domain": "",
    "stamina": "4",
    "staminaIsVar": false,
    "effect": "Адэнидд делает заклинателя легче, позволяя вместо падения плавно спланировать — за каждые 2 метра падения он перемещается на 2 метра в определённом направлении. Если за время действия заклинания заклинатель достигнет земли, он не получит урона от падения.",
    "range": "на себя",
    "duration": "Актив(2 вын)",
    "defence": "нет",
    "components": "",
    "alternateComponents": "",
    "preparationTime": "",
    "dificultyCheck": "",
    "danger": "",
    "liftRequirement": "",
    "sideEffect": "",
    "createTemplate": false,
    "templateSize": "",
    "templateType": "",
    "causeDamages": false,
    "damage": "",
    "effects": [
      {
        "id": "first",
        "name": "effect"
      }
    ]
  },
  "_stats": {
    "systemId": "TheWitcherTRPG",
    "systemVersion": "0.96",
    "coreVersion": "11.304",
    "createdTime": 1668162892151,
    "modifiedTime": 1689232522826,
    "lastModifiedBy": "Rcr49y7kKhnhIeHT"
  },
  "_id": "hqI6yJBIeXtYtaj3",
  "folder": "wsj51D7oIARoDcDr",
  "sort": 0,
  "ownership": {
    "default": 0,
    "TzUlXsBoDDaZxlVp": 3
  },
  "_key": "!items!hqI6yJBIeXtYtaj3"
}