{
  "name": "Воды очищения",
  "type": "spell",
  "img": "icons/magic/water/water-drop-swirl-blue.webp",
  "effects": [],
  "flags": {
    "cf": {
      "id": "temp_so5hsxssqwc"
    },
    "autoanimations": {
      "id": "45af3526-1197-4482-a8c8-d10c2ebf97b7",
      "label": "Воды очищения",
      "levels3d": {
        "type": "explosion",
        "data": {
          "color01": "#FFFFFF",
          "color02": "#FFFFFF",
          "spritePath": "modules/levels-3d-preview/assets/particles/dust.png"
        },
        "sound": {
          "enable": false
        },
        "secondary": {
          "enable": false,
          "data": {
            "color01": "#FFFFFF",
            "color02": "#FFFFFF",
            "spritePath": "modules/levels-3d-preview/assets/particles/dust.png"
          }
        }
      },
      "macro": {
        "enable": false,
        "playWhen": "0"
      },
      "menu": "ontoken",
      "primary": {
        "video": {
          "dbSection": "static",
          "menuType": "energy",
          "animation": "sparkles",
          "variant": "01",
          "color": "blue",
          "enableCustom": false,
          "customPath": ""
        },
        "sound": {
          "enable": false,
          "delay": 0,
          "repeat": 1,
          "repeatDelay": 250,
          "startTime": 0,
          "volume": 0.75
        },
        "options": {
          "addTokenWidth": false,
          "anchor": "0.5",
          "contrast": 0,
          "delay": 0,
          "elevation": 1000,
          "fadeIn": 250,
          "fadeOut": 500,
          "isMasked": false,
          "isRadius": false,
          "isWait": false,
          "opacity": 1,
          "persistent": false,
          "playbackRate": 1,
          "playOn": "target",
          "repeat": 1,
          "repeatDelay": 250,
          "saturate": 0,
          "size": 1,
          "tint": false,
          "tintColor": "#FFFFFF",
          "unbindAlpha": false,
          "unbindVisibility": false,
          "zIndex": 1
        }
      },
      "secondary": {
        "enable": false,
        "video": {
          "dbSection": "static",
          "menuType": "spell",
          "animation": "curewounds",
          "variant": "01",
          "color": "blue",
          "enableCustom": false,
          "customPath": ""
        },
        "sound": {
          "enable": false,
          "delay": 0,
          "repeat": 1,
          "repeatDelay": 250,
          "startTime": 0,
          "volume": 0.75
        },
        "options": {
          "addTokenWidth": false,
          "anchor": "0.5",
          "contrast": 0,
          "delay": 0,
          "elevation": 1000,
          "fadeIn": 250,
          "fadeOut": 500,
          "isMasked": false,
          "isRadius": true,
          "isWait": false,
          "opacity": 1,
          "repeat": 1,
          "repeatDelay": 250,
          "saturate": 0,
          "size": 1.5,
          "tint": false,
          "tintColor": "#FFFFFF",
          "zIndex": 1
        }
      },
      "soundOnly": {
        "sound": {
          "enable": false,
          "delay": 0,
          "repeat": 1,
          "repeatDelay": 250,
          "startTime": 0,
          "volume": 0.75
        }
      },
      "source": {
        "enable": false,
        "video": {
          "dbSection": "static",
          "menuType": "spell",
          "animation": "curewounds",
          "variant": "01",
          "color": "blue",
          "enableCustom": false,
          "customPath": ""
        },
        "sound": {
          "enable": false,
          "delay": 0,
          "repeat": 1,
          "repeatDelay": 250,
          "startTime": 0,
          "volume": 0.75
        },
        "options": {
          "addTokenWidth": false,
          "anchor": "0.5",
          "contrast": 0,
          "delay": 0,
          "elevation": 1000,
          "fadeIn": 250,
          "fadeOut": 500,
          "isMasked": false,
          "isRadius": false,
          "isWait": true,
          "opacity": 1,
          "repeat": 1,
          "repeatDelay": 250,
          "saturate": 0,
          "size": 1,
          "tint": false,
          "tintColor": "#FFFFFF",
          "zIndex": 1
        }
      },
      "target": {
        "enable": false,
        "video": {
          "dbSection": "static",
          "menuType": "spell",
          "animation": "curewounds",
          "variant": "01",
          "color": "blue",
          "enableCustom": false,
          "customPath": ""
        },
        "sound": {
          "enable": false,
          "delay": 0,
          "repeat": 1,
          "repeatDelay": 250,
          "startTime": 0,
          "volume": 0.75
        },
        "options": {
          "addTokenWidth": false,
          "anchor": "0.5",
          "contrast": 0,
          "delay": 0,
          "elevation": 1000,
          "fadeIn": 250,
          "fadeOut": 500,
          "isMasked": false,
          "isRadius": false,
          "opacity": 1,
          "persistent": false,
          "repeat": 1,
          "repeatDelay": 250,
          "saturate": 0,
          "size": 1,
          "tint": false,
          "tintColor": "#FFFFFF",
          "unbindAlpha": false,
          "unbindVisibility": false,
          "zIndex": 1
        }
      },
      "isEnabled": true,
      "isCustomized": true,
      "fromAmmo": false,
      "version": 5
    }
  },
  "system": {
    "class": "Invocations",
    "level": "novice",
    "source": "preacher",
    "domain": "",
    "stamina": "1",
    "staminaIsVar": false,
    "effect": "Воды очищения мгновенно протрезвляют цель. Инвокация нивелирует эффекты крепкого алкоголя и алхимических составов, вызывающих опьянение.",
    "range": "5м",
    "duration": "мгновенная",
    "defence": "сопр магии",
    "components": "",
    "alternateComponents": "",
    "preparationTime": "",
    "dificultyCheck": "",
    "danger": "",
    "liftRequirement": "",
    "sideEffect": "",
    "createTemplate": false,
    "templateSize": "",
    "templateType": "",
    "causeDamages": false,
    "damage": "",
    "effects": [
      {
        "id": "first",
        "name": "effect"
      }
    ]
  },
  "_stats": {
    "systemId": "TheWitcherTRPG",
    "systemVersion": "0.96",
    "coreVersion": "11.304",
    "createdTime": 1668162892155,
    "modifiedTime": 1689193866317,
    "lastModifiedBy": "Rcr49y7kKhnhIeHT"
  },
  "_id": "znM3gKFe7mkHaAqN",
  "folder": "1A4gsGOBCXBnvFaS",
  "sort": 0,
  "ownership": {
    "default": 0,
    "TzUlXsBoDDaZxlVp": 3
  },
  "_key": "!items!znM3gKFe7mkHaAqN"
}