{
  "name": "Атака",
  "type": "weapon",
  "_id": "pFA2jV3gYthJBRcb",
  "img": "icons/skills/melee/blade-tips-triple-bent-white.webp",
  "system": {
    "description": "",
    "quantity": 1,
    "weight": 0,
    "cost": 0,
    "isHidden": false,
    "associatedDiagram": {},
    "type": {
      "text": "Колющий",
      "slashing": false,
      "piercing": true,
      "bludgeoning": false,
      "elemental": false
    },
    "isAmmo": false,
    "usingAmmo": false,
    "accuracy": 0,
    "avail": "Everywhere",
    "damage": "7d6",
    "reliable": 0,
    "maxReliability": 0,
    "hands": "1",
    "range": "4",
    "equiped": false,
    "effects": [],
    "conceal": "T",
    "enhancements": 0,
    "enhancementItems": [],
    "rateOfFire": 1,
    "attackSkill": "Brawling",
    "rollOnlyDmg": true
  },
  "effects": [],
  "folder": null,
  "sort": 0,
  "ownership": {
    "default": 0,
    "TzUlXsBoDDaZxlVp": 3
  },
  "flags": {},
  "_stats": {
    "systemId": "TheWitcherTRPG",
    "systemVersion": "0.94",
    "coreVersion": "10.288",
    "createdTime": 1668183086994,
    "modifiedTime": 1668183114080,
    "lastModifiedBy": "TzUlXsBoDDaZxlVp"
  },
  "_key": "!actors.items!ubwXdjONlXCmzErP.pFA2jV3gYthJBRcb"
}