{
  "name": "Помет беса",
  "type": "component",
  "img": "modules/the-ultimate-witcher/assets/reagents/substances/monsters/dust_gargoyle_64x64.png.6878.png",
  "effects": [],
  "flags": {
    "cf": {
      "id": "temp_3c3due15ne4",
      "color": "#b7f35e"
    },
    "core": {
      "sourceId": "Compendium.the-ultimate-witcher.komponenty.QaOLTljeu1T1xrhW"
    }
  },
  "system": {
    "description": "",
    "quantity": 1,
    "weight": 1,
    "cost": 106,
    "isHidden": false,
    "associatedDiagram": {},
    "type": "substances",
    "rarity": "Rare",
    "location": "Fiends Territory",
    "quantityObtainable": "1d6/2",
    "forage": "20",
    "substanceType": "caelum"
  },
  "_stats": {
    "systemId": "TheWitcherTRPG",
    "systemVersion": "0.96",
    "coreVersion": "11.299",
    "createdTime": 1668162853703,
    "modifiedTime": 1685496603524,
    "lastModifiedBy": "SFdeLroDgLgy3uI9"
  },
  "ownership": {
    "default": 0,
    "TzUlXsBoDDaZxlVp": 3,
    "05FnK6TtcvMYb9FD": 3
  },
  "folder": "UbFFcpt1rc9xdlDQ",
  "sort": 0,
  "_id": "B4V3sFvmwiG3BURi",
  "_key": "!items!B4V3sFvmwiG3BURi"
}